pycoze/__init__.py
pycoze/ai/__init__.py
pycoze/ai/llm/__init__.py
pycoze/ai/llm/chat.py
pycoze/ai/llm/text_to_image_prompt.py
pycoze/api/__init__.py
pycoze/api/lib/__init__.py
pycoze/api/lib/tab.py
pycoze/api/lib/view.py
pycoze/api/lib/web.py
pycoze/api/lib/window.py
pycoze/bot/__init__.py
pycoze/bot/chat.py
pycoze/bot/chat_base.py
pycoze/bot/lib.py
pycoze/bot/message.py
pycoze/bot/prompt.md
pycoze/bot/tools.py
pycoze/reference/__init__.py
pycoze/reference/bot.py
pycoze/reference/fn.py
pycoze/reference/lib.py
pycoze/reference/tool.py
pycoze/reference/workflow.py
pycoze/ui/__init__.py
pycoze/ui/base.py
pycoze/ui/color.py
pycoze/ui/typ.py
pycoze/ui/ui_def.py
pycoze/utils/__init__.py
pycoze/utils/arg.py
pycoze/utils/env.py
pycoze/utils/process.py
pycoze/utils/socket.py
pycoze/utils/text_or_file.py
pycoze/utils/web.py
pycoze-0.1.494.dist-info/LICENSE
pycoze-0.1.494.dist-info/METADATA
pycoze-0.1.494.dist-info/WHEEL
pycoze-0.1.494.dist-info/top_level.txt
pycoze-0.1.494.dist-info/RECORD
