Metadata-Version: 2.2
Name: pycoze
Version: 0.1.494
Summary: Package for pycoze only!
Author: Yuan Jie Xiong
Author-email: aiqqqqqqq@qq.com
Classifier: Programming Language :: Python :: 3
Classifier: License :: OSI Approved :: MIT License
Classifier: Operating System :: OS Independent
Requires-Python: >=3.6
License-File: LICENSE
Dynamic: author
Dynamic: author-email
Dynamic: classifier
Dynamic: description
Dynamic: description-content-type
Dynamic: requires-python
Dynamic: summary
